{
  "hash": "62e3a755",
  "configHash": "c24c5b3c",
  "lockfileHash": "e08bbab0",
  "browserHash": "788c6f36",
  "optimized": {
    "react": {
      "src": "../../node_modules/react/index.js",
      "file": "react.js",
      "fileHash": "a8a04f7e",
      "needsInterop": true
    },
    "react-dom/client": {
      "src": "../../node_modules/react-dom/client.js",
      "file": "react-dom_client.js",
      "fileHash": "75aeea75",
      "needsInterop": true
    },
    "react-redux": {
      "src": "../../node_modules/react-redux/dist/react-redux.mjs",
      "file": "react-redux.js",
      "fileHash": "b907f67b",
      "needsInterop": false
    },
    "@reduxjs/toolkit": {
      "src": "../../node_modules/@reduxjs/toolkit/dist/redux-toolkit.modern.mjs",
      "file": "@reduxjs_toolkit.js",
      "fileHash": "7b951b60",
      "needsInterop": false
    },
    "react-router-dom": {
      "src": "../../node_modules/react-router-dom/dist/index.js",
      "file": "react-router-dom.js",
      "fileHash": "75b4e8de",
      "needsInterop": false
    },
    "table-plugin-react-ts": {
      "src": "../../node_modules/table-plugin-react-ts/dist/main.js",
      "file": "table-plugin-react-ts.js",
      "fileHash": "3e6c8961",
      "needsInterop": false
    }
  },
  "chunks": {
    "chunk-5IFATXZH": {
      "file": "chunk-5IFATXZH.js"
    },
    "chunk-URNRBCZE": {
      "file": "chunk-URNRBCZE.js"
    },
    "chunk-LNEMQRCO": {
      "file": "chunk-LNEMQRCO.js"
    }
  }
}